<?xml version="1.0"?>
<!DOCTYPE I2CEConfiguration SYSTEM "I2CE_Configuration.dtd">
<I2CEConfiguration name="localeSelector">
  <metadata>
    <displayName>Locale Selector</displayName>
    <className>I2CE_Module_LocaleSelector</className>
    <version>4.2.1.0</version>
  </metadata>
  <configurationGroup name="localeSelector" locale="sl">
    <configuration name="languages" path="/locales/languages" values="many" type="delimited">
      <version>4.0.0</version>
      <value>aa:afarsko</value>
      <value>ab:abkazijansko</value>
      <value>ae:avestansko</value>
      <value>af:afrikansko</value>
      <value>am:amharik</value>
      <value>ar:arabsko</value>
      <value>as:asamese</value>
      <value>ay:ajmarsko</value>
      <value>az:azerbajd&#382;ansko</value>
      <value>ba:ba&#353;kirsko</value>
      <value>be:belorusko</value>
      <value>bg:bolgarsko</value>
      <value>bh:bihari</value>
      <value>bi:bislama</value>
      <value>bn:bengalsko</value>
      <value>bo:tibetansko</value>
      <value>br:bretonsko</value>
      <value>bs:bosansko</value>
      <value>ca:katalonsko</value>
      <value>ce:&#269;e&#269;ensko</value>
      <value>ch:chamorro</value>
      <value>co:korzij&#353;ko</value>
      <value>cs:&#269;e&#353;ko</value>
      <value>cu:cerkvena slovan&#353;&#269;ina</value>
      <value>cv:chuvash</value>
      <value>cy:vali&#382;ansko</value>
      <value>da:dansko</value>
      <value>de:nem&#353;ko</value>
      <value>dz:dzonkha</value>
      <value>el:gr&#353;ko</value>
      <value>en:angle&#353;ko</value>
      <value>en_GB:britansko angle&#353;ko</value>
      <value>en_US:ameri&#353;ko angle&#353;ko</value>
      <value>eo:esperanto</value>
      <value>es:&#353;pansko</value>
      <value>et:estonsko</value>
      <value>eu:baskovsko</value>
      <value>fa:Farsi (perzijsko)</value>
      <value>fi:finsko</value>
      <value>fj:fid&#382;ijsko</value>
      <value>fo:fersko</value>
      <value>fr:francosko</value>
      <value>fy:frizijsko</value>
      <value>ga:irsko galsko</value>
      <value>gd:galsko</value>
      <value>gl:galicijsko</value>
      <value>gn:guarani</value>
      <value>gu:gujarati</value>
      <value>gv:manx</value>
      <value>ha:hausa</value>
      <value>he:hebrejsko</value>
      <value>hi:hindujsko</value>
      <value>ho:hiri motu</value>
      <value>hr:hrva&#353;ko</value>
      <value>hsb:zgornjesorbijsko</value>
      <value>hu:mad&#382;arsko</value>
      <value>hy:armensko</value>
      <value>hz:herero</value>
      <value>ia:interlingua</value>
      <value>id:indonezijsko</value>
      <value>ie:interlingue</value>
      <value>ik:inupiaq</value>
      <value>io:ido</value>
      <value>is:islandsko</value>
      <value>it:italijansko</value>
      <value>iu:inuktitut</value>
      <value>ja:japonsko</value>
      <value>jv:javansko</value>
      <value>ka:gruzijsko</value>
      <value>ki:kikuyu</value>
      <value>kk:kaza&#353;ko</value>
      <value>kl:kalaallisut</value>
      <value>km:kmersko</value>
      <value>kn:kannada</value>
      <value>ko:korejsko</value>
      <value>ks:ka&#353;mirsko</value>
      <value>ku:kurdsko</value>
      <value>kv:komi</value>
      <value>kw:cornish</value>
      <value>ky:kirgizijsko</value>
      <value>la:latinsko</value>
      <value>lb:luksembur&#353;ko</value>
      <value>li:limburgan</value>
      <value>ln:lingala</value>
      <value>lo:lao&#353;ko</value>
      <value>lt:litvansko</value>
      <value>lv:latvijsko</value>
      <value>mg:malaga&#353;ko</value>
      <value>mh:mar&#353;alsko</value>
      <value>mi:maorsko</value>
      <value>mk:makedonsko</value>
      <value>ml:malayalam</value>
      <value>mn:mongolsko</value>
      <value>mo:moldavsko</value>
      <value>mr:marathi</value>
      <value>ms:malajsko</value>
      <value>mt:malte&#382;ansko</value>
      <value>my:burmansko</value>
      <value>na:nauru</value>
      <value>nb:norve&#353;ko (bokmaal)</value>
      <value>nd:ndebele, severno</value>
      <value>nds:spodnjesa&#353;ko</value>
      <value>ne:nepalsko</value>
      <value>ng:ndonga</value>
      <value>nl:nizozemsko</value>
      <value>nn:norve&#353;ko (nyorsk)</value>
      <value>nr:ndebele, ju&#382;no</value>
      <value>nso:severni sotho</value>
      <value>nv:navajo</value>
      <value>ny:chichewa</value>
      <value>oc:o&#269;itansko</value>
      <value>om:oromo</value>
      <value>or:oriya</value>
      <value>os:osetijsko</value>
      <value>pa:pand&#382;absko</value>
      <value>pi:pali</value>
      <value>pl:poljsko</value>
      <value>ps:pushto</value>
      <value>pt:portugalsko</value>
      <value>pt_BR:brazilska portugal&#353;&#269;ina</value>
      <value>qu:quechua</value>
      <value>rn:rundi</value>
      <value>ro:romunsko</value>
      <value>rom:romsko</value>
      <value>ru:rusko</value>
      <value>rw:kinyarwanda</value>
      <value>sa:sanskrt</value>
      <value>sc:sardinsko</value>
      <value>sd:sindijsko</value>
      <value>se:severno sami</value>
      <value>sg:sango</value>
      <value>si:sinhalese</value>
      <value>sk:slova&#353;ko</value>
      <value>sl:slovensko</value>
      <value>sm:samojsko</value>
      <value>sn:shona</value>
      <value>so:somalsko</value>
      <value>sq:albansko</value>
      <value>sr:srbsko latinsko</value>
      <value>ss:swati</value>
      <value>st:sotho, ju&#382;ni</value>
      <value>su:sudansko</value>
      <value>sv:&#353;vedsko</value>
      <value>sw:svahili</value>
      <value>ta:tamilsko</value>
      <value>te:telugu</value>
      <value>tg:tad&#382;i&#353;ko</value>
      <value>th:tajsko</value>
      <value>ti:tigrinya</value>
      <value>tk:turkmensko</value>
      <value>tn:tswana</value>
      <value>to:tonga&#353;ko</value>
      <value>tr:tur&#353;ko</value>
      <value>ts:tsonga</value>
      <value>tt:tatarsko</value>
      <value>tw:twi</value>
      <value>ty:tahitijsko</value>
      <value>ug:ujgursko</value>
      <value>uk:ukrajinsko</value>
      <value>ur:urdu</value>
      <value>uz:uzbe&#353;ko</value>
      <value>ven:venda</value>
      <value>vi:vietnamsko</value>
      <value>vo:volap&#252;k</value>
      <value>wa:walloonsko</value>
      <value>wo:wolof</value>
      <value>xh:xhosa</value>
      <value>yi:yiddish</value>
      <value>yo:yoruba</value>
      <value>za:zhuang</value>
      <value>zh:kitajsko</value>
      <value>zh_CN:poenostavljeno kitajsko</value>
      <value>zh_HK:kitajsko (Hong Kong)</value>
      <value>zh_TW:tradicionalno kitajsko</value>
      <value>zu:zulu</value>
    </configuration>
  </configurationGroup>
</I2CEConfiguration>