<?xml version="1.0"?>
<!DOCTYPE I2CEConfiguration SYSTEM "I2CE_Configuration.dtd">
<I2CEConfiguration name="Uganda-standard-data-org_support">
  <metadata>
    <displayName>Uganda-standard-data: org_support</displayName>
    <description>Uganda-standard-data: org_support data</description>
    <version>4.2.1</version>
  </metadata>
  <configurationGroup name="Uganda-standard-data-org_support" path="//I2CE/formsData/forms/org_support">
    <displayName>Export</displayName>
    <version>4.2.1</version>
    <configurationGroup name="1">
      <displayName>1</displayName>
      <configurationGroup name="fields">
        <displayName>Fields</displayName>
        <configuration name="i2ce_hidden">
          <displayName>I2ce Hidden</displayName>
          <value>0</value>
        </configuration>
        <configuration name="name">
          <displayName>Name</displayName>
          <value>UNICEF</value>
        </configuration>
        <configuration name="remap">
          <displayName>Remap</displayName>
          <value></value>
        </configuration>
      </configurationGroup>
      <configuration name="last_modified">
        <displayName>Last Modified</displayName>
        <value>2016-11-02 14:22:29</value>
      </configuration>
      <configuration name="who">
        <displayName>Who</displayName>
        <value>0</value>
      </configuration>
    </configurationGroup>
    <configurationGroup name="10">
      <displayName>10</displayName>
      <configurationGroup name="fields">
        <displayName>Fields</displayName>
        <configuration name="i2ce_hidden">
          <displayName>I2ce Hidden</displayName>
          <value>0</value>
        </configuration>
        <configuration name="name">
          <displayName>Name</displayName>
          <value>Welshare International</value>
        </configuration>
        <configuration name="remap">
          <displayName>Remap</displayName>
          <value></value>
        </configuration>
      </configurationGroup>
      <configuration name="last_modified">
        <displayName>Last Modified</displayName>
        <value>2016-11-07 18:11:22</value>
      </configuration>
      <configuration name="who">
        <displayName>Who</displayName>
        <value>53</value>
      </configuration>
    </configurationGroup>
    <configurationGroup name="11">
      <displayName>11</displayName>
      <configurationGroup name="fields">
        <displayName>Fields</displayName>
        <configuration name="i2ce_hidden">
          <displayName>I2ce Hidden</displayName>
          <value>0</value>
        </configuration>
        <configuration name="name">
          <displayName>Name</displayName>
          <value>Mercy Corps</value>
        </configuration>
        <configuration name="remap">
          <displayName>Remap</displayName>
          <value></value>
        </configuration>
      </configurationGroup>
      <configuration name="last_modified">
        <displayName>Last Modified</displayName>
        <value>2016-11-07 18:11:48</value>
      </configuration>
      <configuration name="who">
        <displayName>Who</displayName>
        <value>53</value>
      </configuration>
    </configurationGroup>
    <configurationGroup name="12">
      <displayName>12</displayName>
      <configurationGroup name="fields">
        <displayName>Fields</displayName>
        <configuration name="i2ce_hidden">
          <displayName>I2ce Hidden</displayName>
          <value>0</value>
        </configuration>
        <configuration name="name">
          <displayName>Name</displayName>
          <value>RHITES</value>
        </configuration>
        <configuration name="remap">
          <displayName>Remap</displayName>
          <value></value>
        </configuration>
      </configurationGroup>
      <configuration name="last_modified">
        <displayName>Last Modified</displayName>
        <value>2016-11-07 18:12:08</value>
      </configuration>
      <configuration name="who">
        <displayName>Who</displayName>
        <value>53</value>
      </configuration>
    </configurationGroup>
    <configurationGroup name="13">
      <displayName>13</displayName>
      <configurationGroup name="fields">
        <displayName>Fields</displayName>
        <configuration name="i2ce_hidden">
          <displayName>I2ce Hidden</displayName>
          <value>0</value>
        </configuration>
        <configuration name="name">
          <displayName>Name</displayName>
          <value>PATH</value>
        </configuration>
        <configuration name="remap">
          <displayName>Remap</displayName>
          <value></value>
        </configuration>
      </configurationGroup>
      <configuration name="last_modified">
        <displayName>Last Modified</displayName>
        <value>2016-11-07 18:12:29</value>
      </configuration>
      <configuration name="who">
        <displayName>Who</displayName>
        <value>53</value>
      </configuration>
    </configurationGroup>
    <configurationGroup name="14">
      <displayName>14</displayName>
      <configurationGroup name="fields">
        <displayName>Fields</displayName>
        <configuration name="i2ce_hidden">
          <displayName>I2ce Hidden</displayName>
          <value>0</value>
        </configuration>
        <configuration name="name">
          <displayName>Name</displayName>
          <value>FHI360</value>
        </configuration>
        <configuration name="remap">
          <displayName>Remap</displayName>
          <value></value>
        </configuration>
      </configurationGroup>
      <configuration name="last_modified">
        <displayName>Last Modified</displayName>
        <value>2016-11-07 18:12:54</value>
      </configuration>
      <configuration name="who">
        <displayName>Who</displayName>
        <value>53</value>
      </configuration>
    </configurationGroup>
    <configurationGroup name="15">
      <displayName>15</displayName>
      <configurationGroup name="fields">
        <displayName>Fields</displayName>
        <configuration name="i2ce_hidden">
          <displayName>I2ce Hidden</displayName>
          <value>0</value>
        </configuration>
        <configuration name="name">
          <displayName>Name</displayName>
          <value>MJAP</value>
        </configuration>
        <configuration name="remap">
          <displayName>Remap</displayName>
          <value></value>
        </configuration>
      </configurationGroup>
      <configuration name="last_modified">
        <displayName>Last Modified</displayName>
        <value>2016-11-07 18:13:16</value>
      </configuration>
      <configuration name="who">
        <displayName>Who</displayName>
        <value>53</value>
      </configuration>
    </configurationGroup>
    <configurationGroup name="2">
      <displayName>2</displayName>
      <configurationGroup name="fields">
        <displayName>Fields</displayName>
        <configuration name="i2ce_hidden">
          <displayName>I2ce Hidden</displayName>
          <value>0</value>
        </configuration>
        <configuration name="name">
          <displayName>Name</displayName>
          <value>CONCERN</value>
        </configuration>
        <configuration name="remap">
          <displayName>Remap</displayName>
          <value></value>
        </configuration>
      </configurationGroup>
      <configuration name="last_modified">
        <displayName>Last Modified</displayName>
        <value>2016-11-02 14:22:41</value>
      </configuration>
      <configuration name="who">
        <displayName>Who</displayName>
        <value>0</value>
      </configuration>
    </configurationGroup>
    <configurationGroup name="3">
      <displayName>3</displayName>
      <configurationGroup name="fields">
        <displayName>Fields</displayName>
        <configuration name="i2ce_hidden">
          <displayName>I2ce Hidden</displayName>
          <value>0</value>
        </configuration>
        <configuration name="name">
          <displayName>Name</displayName>
          <value>Baylor Uganda</value>
        </configuration>
        <configuration name="remap">
          <displayName>Remap</displayName>
          <value></value>
        </configuration>
      </configurationGroup>
      <configuration name="last_modified">
        <displayName>Last Modified</displayName>
        <value>2016-11-02 14:23:00</value>
      </configuration>
      <configuration name="who">
        <displayName>Who</displayName>
        <value>0</value>
      </configuration>
    </configurationGroup>
    <configurationGroup name="4">
      <displayName>4</displayName>
      <configurationGroup name="fields">
        <displayName>Fields</displayName>
        <configuration name="i2ce_hidden">
          <displayName>I2ce Hidden</displayName>
          <value>0</value>
        </configuration>
        <configuration name="name">
          <displayName>Name</displayName>
          <value>Community Action for Health</value>
        </configuration>
        <configuration name="remap">
          <displayName>Remap</displayName>
          <value></value>
        </configuration>
      </configurationGroup>
      <configuration name="last_modified">
        <displayName>Last Modified</displayName>
        <value>2016-11-02 14:23:30</value>
      </configuration>
      <configuration name="who">
        <displayName>Who</displayName>
        <value>0</value>
      </configuration>
    </configurationGroup>
    <configurationGroup name="5">
      <displayName>5</displayName>
      <configurationGroup name="fields">
        <displayName>Fields</displayName>
        <configuration name="i2ce_hidden">
          <displayName>I2ce Hidden</displayName>
          <value>0</value>
        </configuration>
        <configuration name="name">
          <displayName>Name</displayName>
          <value>TASO</value>
        </configuration>
        <configuration name="remap">
          <displayName>Remap</displayName>
          <value></value>
        </configuration>
      </configurationGroup>
      <configuration name="last_modified">
        <displayName>Last Modified</displayName>
        <value>2016-11-07 18:09:17</value>
      </configuration>
      <configuration name="who">
        <displayName>Who</displayName>
        <value>53</value>
      </configuration>
    </configurationGroup>
    <configurationGroup name="6">
      <displayName>6</displayName>
      <configurationGroup name="fields">
        <displayName>Fields</displayName>
        <configuration name="i2ce_hidden">
          <displayName>I2ce Hidden</displayName>
          <value>0</value>
        </configuration>
        <configuration name="name">
          <displayName>Name</displayName>
          <value>MUWRP</value>
        </configuration>
        <configuration name="remap">
          <displayName>Remap</displayName>
          <value></value>
        </configuration>
      </configurationGroup>
      <configuration name="last_modified">
        <displayName>Last Modified</displayName>
        <value>2016-11-07 18:09:40</value>
      </configuration>
      <configuration name="who">
        <displayName>Who</displayName>
        <value>53</value>
      </configuration>
    </configurationGroup>
    <configurationGroup name="7">
      <displayName>7</displayName>
      <configurationGroup name="fields">
        <displayName>Fields</displayName>
        <configuration name="i2ce_hidden">
          <displayName>I2ce Hidden</displayName>
          <value>0</value>
        </configuration>
        <configuration name="name">
          <displayName>Name</displayName>
          <value>STAR-EC</value>
        </configuration>
        <configuration name="remap">
          <displayName>Remap</displayName>
          <value></value>
        </configuration>
      </configurationGroup>
      <configuration name="last_modified">
        <displayName>Last Modified</displayName>
        <value>2016-11-07 18:10:08</value>
      </configuration>
      <configuration name="who">
        <displayName>Who</displayName>
        <value>53</value>
      </configuration>
    </configurationGroup>
    <configurationGroup name="8">
      <displayName>8</displayName>
      <configurationGroup name="fields">
        <displayName>Fields</displayName>
        <configuration name="i2ce_hidden">
          <displayName>I2ce Hidden</displayName>
          <value>0</value>
        </configuration>
        <configuration name="name">
          <displayName>Name</displayName>
          <value>IDI</value>
        </configuration>
        <configuration name="remap">
          <displayName>Remap</displayName>
          <value></value>
        </configuration>
      </configurationGroup>
      <configuration name="last_modified">
        <displayName>Last Modified</displayName>
        <value>2016-11-07 18:10:29</value>
      </configuration>
      <configuration name="who">
        <displayName>Who</displayName>
        <value>53</value>
      </configuration>
    </configurationGroup>
    <configurationGroup name="9">
      <displayName>9</displayName>
      <configurationGroup name="fields">
        <displayName>Fields</displayName>
        <configuration name="i2ce_hidden">
          <displayName>I2ce Hidden</displayName>
          <value>0</value>
        </configuration>
        <configuration name="name">
          <displayName>Name</displayName>
          <value>USAID/CHC Obulamu Campaign</value>
        </configuration>
        <configuration name="remap">
          <displayName>Remap</displayName>
          <value></value>
        </configuration>
      </configurationGroup>
      <configuration name="last_modified">
        <displayName>Last Modified</displayName>
        <value>2016-11-07 18:10:53</value>
      </configuration>
      <configuration name="who">
        <displayName>Who</displayName>
        <value>53</value>
      </configuration>
    </configurationGroup>
  </configurationGroup>
</I2CEConfiguration>